piidetect/__init__.py
piidetect/fakepii.py
piidetect/pipeline.py
piidetect-0.0.0.2.dist-info/METADATA
piidetect-0.0.0.2.dist-info/WHEEL
piidetect-0.0.0.2.dist-info/top_level.txt
piidetect-0.0.0.2.dist-info/RECORD
