Metadata-Version: 2.1
Name: piidetect
Version: 0.0.0.2
Summary: A package to build an end-to-end ML pipeline to detect personally identifiable information from text. 
Home-page: https://github.com/edwardcooper/piidetect
Author: Edward Lu
Author-email: maxminicherrycc@gmail.com
License: UNKNOWN
Platform: UNKNOWN
Classifier: Programming Language :: Python :: 3
Classifier: License :: OSI Approved :: MIT License
Classifier: Operating System :: OS Independent
Requires-Dist: gensim
Requires-Dist: numpy
Requires-Dist: pandas
Requires-Dist: faker
Requires-Dist: tqdm
Requires-Dist: sklearn
